{"nodes": [{"id": "c_users_johns_source_repos_mediabox2026_mediabox2026_components_pages_watchlist_razor", "label": "Watchlist.razor", "file_type": "code", "source_file": "C:\\Users\\johns\\source\\repos\\MediaBox2026\\MediaBox2026\\Components\\Pages\\Watchlist.razor", "source_location": null}, {"id": "route_watchlist", "label": "route:/watchlist", "file_type": "concept", "source_file": "C:\\Users\\johns\\source\\repos\\MediaBox2026\\MediaBox2026\\Components\\Pages\\Watchlist.razor", "source_location": "L1"}, {"id": "mediabox2026_services", "label": "MediaBox2026.Services", "file_type": "code", "source_file": "C:\\Users\\johns\\source\\repos\\MediaBox2026\\MediaBox2026\\Components\\Pages\\Watchlist.razor", "source_location": "L2"}, {"id": "mediabox2026_models", "label": "MediaBox2026.Models", "file_type": "code", "source_file": "C:\\Users\\johns\\source\\repos\\MediaBox2026\\MediaBox2026\\Components\\Pages\\Watchlist.razor", "source_location": "L3"}, {"id": "mediadatabase", "label": "MediaDatabase", "file_type": "code", "source_file": "C:\\Users\\johns\\source\\repos\\MediaBox2026\\MediaBox2026\\Components\\Pages\\Watchlist.razor", "source_location": "L4"}, {"id": "mediaboxstate", "label": "MediaBoxState", "file_type": "code", "source_file": "C:\\Users\\johns\\source\\repos\\MediaBox2026\\MediaBox2026\\Components\\Pages\\Watchlist.razor", "source_location": "L5"}, {"id": "pagetitle", "label": "PageTitle", "file_type": "code", "source_file": "C:\\Users\\johns\\source\\repos\\MediaBox2026\\MediaBox2026\\Components\\Pages\\Watchlist.razor", "source_location": "L8"}, {"id": "watchlistitem", "label": "WatchlistItem", "file_type": "code", "source_file": "C:\\Users\\johns\\source\\repos\\MediaBox2026\\MediaBox2026\\Components\\Pages\\Watchlist.razor", "source_location": "L65"}, {"id": "pages_watchlist_oninitialized", "label": "OnInitialized", "file_type": "code", "source_file": "C:\\Users\\johns\\source\\repos\\MediaBox2026\\MediaBox2026\\Components\\Pages\\Watchlist.razor", "source_location": "L68"}, {"id": "pages_watchlist_loaddata", "label": "LoadData", "file_type": "code", "source_file": "C:\\Users\\johns\\source\\repos\\MediaBox2026\\MediaBox2026\\Components\\Pages\\Watchlist.razor", "source_location": "L74"}, {"id": "pages_watchlist_addmovie", "label": "AddMovie", "file_type": "code", "source_file": "C:\\Users\\johns\\source\\repos\\MediaBox2026\\MediaBox2026\\Components\\Pages\\Watchlist.razor", "source_location": "L76"}, {"id": "pages_watchlist_removeitem", "label": "RemoveItem", "file_type": "code", "source_file": "C:\\Users\\johns\\source\\repos\\MediaBox2026\\MediaBox2026\\Components\\Pages\\Watchlist.razor", "source_location": "L93"}, {"id": "pages_watchlist_handlekeyup", "label": "HandleKeyUp", "file_type": "code", "source_file": "C:\\Users\\johns\\source\\repos\\MediaBox2026\\MediaBox2026\\Components\\Pages\\Watchlist.razor", "source_location": "L102"}, {"id": "pages_watchlist_getstatusbadge", "label": "GetStatusBadge", "file_type": "code", "source_file": "C:\\Users\\johns\\source\\repos\\MediaBox2026\\MediaBox2026\\Components\\Pages\\Watchlist.razor", "source_location": "L107"}, {"id": "pages_watchlist_onstatechanged", "label": "OnStateChanged", "file_type": "code", "source_file": "C:\\Users\\johns\\source\\repos\\MediaBox2026\\MediaBox2026\\Components\\Pages\\Watchlist.razor", "source_location": "L118"}, {"id": "pages_watchlist_dispose", "label": "Dispose", "file_type": "code", "source_file": "C:\\Users\\johns\\source\\repos\\MediaBox2026\\MediaBox2026\\Components\\Pages\\Watchlist.razor", "source_location": "L120"}], "edges": [{"source": "c_users_johns_source_repos_mediabox2026_mediabox2026_components_pages_watchlist_razor", "target": "route_watchlist", "relation": "references", "confidence": "EXTRACTED", "source_file": "C:\\Users\\johns\\source\\repos\\MediaBox2026\\MediaBox2026\\Components\\Pages\\Watchlist.razor", "weight": 1.0}, {"source": "c_users_johns_source_repos_mediabox2026_mediabox2026_components_pages_watchlist_razor", "target": "mediabox2026_services", "relation": "imports", "confidence": "EXTRACTED", "source_file": "C:\\Users\\johns\\source\\repos\\MediaBox2026\\MediaBox2026\\Components\\Pages\\Watchlist.razor", "source_location": "L2", "weight": 1.0}, {"source": "c_users_johns_source_repos_mediabox2026_mediabox2026_components_pages_watchlist_razor", "target": "mediabox2026_models", "relation": "imports", "confidence": "EXTRACTED", "source_file": "C:\\Users\\johns\\source\\repos\\MediaBox2026\\MediaBox2026\\Components\\Pages\\Watchlist.razor", "source_location": "L3", "weight": 1.0}, {"source": "c_users_johns_source_repos_mediabox2026_mediabox2026_components_pages_watchlist_razor", "target": "mediadatabase", "relation": "imports", "confidence": "EXTRACTED", "source_file": "C:\\Users\\johns\\source\\repos\\MediaBox2026\\MediaBox2026\\Components\\Pages\\Watchlist.razor", "source_location": "L4", "weight": 1.0}, {"source": "c_users_johns_source_repos_mediabox2026_mediabox2026_components_pages_watchlist_razor", "target": "mediaboxstate", "relation": "imports", "confidence": "EXTRACTED", "source_file": "C:\\Users\\johns\\source\\repos\\MediaBox2026\\MediaBox2026\\Components\\Pages\\Watchlist.razor", "source_location": "L5", "weight": 1.0}, {"source": "c_users_johns_source_repos_mediabox2026_mediabox2026_components_pages_watchlist_razor", "target": "pagetitle", "relation": "calls", "confidence": "EXTRACTED", "source_file": "C:\\Users\\johns\\source\\repos\\MediaBox2026\\MediaBox2026\\Components\\Pages\\Watchlist.razor", "source_location": "L8", "weight": 1.0}, {"source": "c_users_johns_source_repos_mediabox2026_mediabox2026_components_pages_watchlist_razor", "target": "watchlistitem", "relation": "calls", "confidence": "EXTRACTED", "source_file": "C:\\Users\\johns\\source\\repos\\MediaBox2026\\MediaBox2026\\Components\\Pages\\Watchlist.razor", "source_location": "L65", "weight": 1.0}, {"source": "c_users_johns_source_repos_mediabox2026_mediabox2026_components_pages_watchlist_razor", "target": "pages_watchlist_oninitialized", "relation": "contains", "confidence": "EXTRACTED", "source_file": "C:\\Users\\johns\\source\\repos\\MediaBox2026\\MediaBox2026\\Components\\Pages\\Watchlist.razor", "weight": 1.0}, {"source": "c_users_johns_source_repos_mediabox2026_mediabox2026_components_pages_watchlist_razor", "target": "pages_watchlist_loaddata", "relation": "contains", "confidence": "EXTRACTED", "source_file": "C:\\Users\\johns\\source\\repos\\MediaBox2026\\MediaBox2026\\Components\\Pages\\Watchlist.razor", "weight": 1.0}, {"source": "c_users_johns_source_repos_mediabox2026_mediabox2026_components_pages_watchlist_razor", "target": "pages_watchlist_addmovie", "relation": "contains", "confidence": "EXTRACTED", "source_file": "C:\\Users\\johns\\source\\repos\\MediaBox2026\\MediaBox2026\\Components\\Pages\\Watchlist.razor", "weight": 1.0}, {"source": "c_users_johns_source_repos_mediabox2026_mediabox2026_components_pages_watchlist_razor", "target": "pages_watchlist_removeitem", "relation": "contains", "confidence": "EXTRACTED", "source_file": "C:\\Users\\johns\\source\\repos\\MediaBox2026\\MediaBox2026\\Components\\Pages\\Watchlist.razor", "weight": 1.0}, {"source": "c_users_johns_source_repos_mediabox2026_mediabox2026_components_pages_watchlist_razor", "target": "pages_watchlist_handlekeyup", "relation": "contains", "confidence": "EXTRACTED", "source_file": "C:\\Users\\johns\\source\\repos\\MediaBox2026\\MediaBox2026\\Components\\Pages\\Watchlist.razor", "weight": 1.0}, {"source": "c_users_johns_source_repos_mediabox2026_mediabox2026_components_pages_watchlist_razor", "target": "pages_watchlist_getstatusbadge", "relation": "contains", "confidence": "EXTRACTED", "source_file": "C:\\Users\\johns\\source\\repos\\MediaBox2026\\MediaBox2026\\Components\\Pages\\Watchlist.razor", "weight": 1.0}, {"source": "c_users_johns_source_repos_mediabox2026_mediabox2026_components_pages_watchlist_razor", "target": "pages_watchlist_onstatechanged", "relation": "contains", "confidence": "EXTRACTED", "source_file": "C:\\Users\\johns\\source\\repos\\MediaBox2026\\MediaBox2026\\Components\\Pages\\Watchlist.razor", "weight": 1.0}, {"source": "c_users_johns_source_repos_mediabox2026_mediabox2026_components_pages_watchlist_razor", "target": "pages_watchlist_dispose", "relation": "contains", "confidence": "EXTRACTED", "source_file": "C:\\Users\\johns\\source\\repos\\MediaBox2026\\MediaBox2026\\Components\\Pages\\Watchlist.razor", "weight": 1.0}]}