{"nodes": [{"id": "c_users_johns_source_repos_mediabox2026_mediabox2026_services_transmissionclient_cs", "label": "TransmissionClient.cs", "file_type": "code", "source_file": "C:\\Users\\johns\\source\\repos\\MediaBox2026\\MediaBox2026\\Services\\TransmissionClient.cs", "source_location": "L1"}, {"id": "services_transmissionclient_transmissionclient", "label": "TransmissionClient", "file_type": "code", "source_file": "C:\\Users\\johns\\source\\repos\\MediaBox2026\\MediaBox2026\\Services\\TransmissionClient.cs", "source_location": "L10"}, {"id": "string", "label": "string", "file_type": "code", "source_file": "C:\\Users\\johns\\source\\repos\\MediaBox2026\\MediaBox2026\\Services\\TransmissionClient.cs", "source_location": "L12"}, {"id": "services_transmissionclient_transmissionclient_addtorrentasync", "label": ".AddTorrentAsync()", "file_type": "code", "source_file": "C:\\Users\\johns\\source\\repos\\MediaBox2026\\MediaBox2026\\Services\\TransmissionClient.cs", "source_location": "L14"}, {"id": "cancellationtoken", "label": "CancellationToken", "file_type": "code", "source_file": "C:\\Users\\johns\\source\\repos\\MediaBox2026\\MediaBox2026\\Services\\TransmissionClient.cs", "source_location": "L14"}, {"id": "task", "label": "Task", "file_type": "code", "source_file": "C:\\Users\\johns\\source\\repos\\MediaBox2026\\MediaBox2026\\Services\\TransmissionClient.cs", "source_location": "L14"}, {"id": "services_transmissionclient_transmissionclient_gettorrentsasync", "label": ".GetTorrentsAsync()", "file_type": "code", "source_file": "C:\\Users\\johns\\source\\repos\\MediaBox2026\\MediaBox2026\\Services\\TransmissionClient.cs", "source_location": "L35"}, {"id": "list", "label": "List", "file_type": "code", "source_file": "C:\\Users\\johns\\source\\repos\\MediaBox2026\\MediaBox2026\\Services\\TransmissionClient.cs", "source_location": "L35"}, {"id": "torrentinfo", "label": "TorrentInfo", "file_type": "code", "source_file": "C:\\Users\\johns\\source\\repos\\MediaBox2026\\MediaBox2026\\Services\\TransmissionClient.cs", "source_location": "L35"}, {"id": "services_transmissionclient_transmissionclient_removetorrentasync", "label": ".RemoveTorrentAsync()", "file_type": "code", "source_file": "C:\\Users\\johns\\source\\repos\\MediaBox2026\\MediaBox2026\\Services\\TransmissionClient.cs", "source_location": "L74"}, {"id": "services_transmissionclient_transmissionclient_pausetorrentasync", "label": ".PauseTorrentAsync()", "file_type": "code", "source_file": "C:\\Users\\johns\\source\\repos\\MediaBox2026\\MediaBox2026\\Services\\TransmissionClient.cs", "source_location": "L89"}, {"id": "services_transmissionclient_transmissionclient_resumetorrentasync", "label": ".ResumeTorrentAsync()", "file_type": "code", "source_file": "C:\\Users\\johns\\source\\repos\\MediaBox2026\\MediaBox2026\\Services\\TransmissionClient.cs", "source_location": "L108"}, {"id": "services_transmissionclient_transmissionclient_getaltspeedenabledasync", "label": ".GetAltSpeedEnabledAsync()", "file_type": "code", "source_file": "C:\\Users\\johns\\source\\repos\\MediaBox2026\\MediaBox2026\\Services\\TransmissionClient.cs", "source_location": "L127"}, {"id": "services_transmissionclient_transmissionclient_setaltspeedasync", "label": ".SetAltSpeedAsync()", "file_type": "code", "source_file": "C:\\Users\\johns\\source\\repos\\MediaBox2026\\MediaBox2026\\Services\\TransmissionClient.cs", "source_location": "L145"}, {"id": "services_transmissionclient_transmissionclient_sendrpcasync", "label": ".SendRpcAsync()", "file_type": "code", "source_file": "C:\\Users\\johns\\source\\repos\\MediaBox2026\\MediaBox2026\\Services\\TransmissionClient.cs", "source_location": "L164"}, {"id": "jsonobject", "label": "JsonObject", "file_type": "code", "source_file": "C:\\Users\\johns\\source\\repos\\MediaBox2026\\MediaBox2026\\Services\\TransmissionClient.cs", "source_location": "L164"}, {"id": "jsonelement", "label": "JsonElement", "file_type": "code", "source_file": "C:\\Users\\johns\\source\\repos\\MediaBox2026\\MediaBox2026\\Services\\TransmissionClient.cs", "source_location": "L164"}], "edges": [{"source": "c_users_johns_source_repos_mediabox2026_mediabox2026_services_transmissionclient_cs", "target": "headers", "relation": "imports", "context": "import", "confidence": "EXTRACTED", "source_file": "C:\\Users\\johns\\source\\repos\\MediaBox2026\\MediaBox2026\\Services\\TransmissionClient.cs", "source_location": "L1", "weight": 1.0}, {"source": "c_users_johns_source_repos_mediabox2026_mediabox2026_services_transmissionclient_cs", "target": "text", "relation": "imports", "context": "import", "confidence": "EXTRACTED", "source_file": "C:\\Users\\johns\\source\\repos\\MediaBox2026\\MediaBox2026\\Services\\TransmissionClient.cs", "source_location": "L2", "weight": 1.0}, {"source": "c_users_johns_source_repos_mediabox2026_mediabox2026_services_transmissionclient_cs", "target": "json", "relation": "imports", "context": "import", "confidence": "EXTRACTED", "source_file": "C:\\Users\\johns\\source\\repos\\MediaBox2026\\MediaBox2026\\Services\\TransmissionClient.cs", "source_location": "L3", "weight": 1.0}, {"source": "c_users_johns_source_repos_mediabox2026_mediabox2026_services_transmissionclient_cs", "target": "nodes", "relation": "imports", "context": "import", "confidence": "EXTRACTED", "source_file": "C:\\Users\\johns\\source\\repos\\MediaBox2026\\MediaBox2026\\Services\\TransmissionClient.cs", "source_location": "L4", "weight": 1.0}, {"source": "c_users_johns_source_repos_mediabox2026_mediabox2026_services_transmissionclient_cs", "target": "models", "relation": "imports", "context": "import", "confidence": "EXTRACTED", "source_file": "C:\\Users\\johns\\source\\repos\\MediaBox2026\\MediaBox2026\\Services\\TransmissionClient.cs", "source_location": "L5", "weight": 1.0}, {"source": "c_users_johns_source_repos_mediabox2026_mediabox2026_services_transmissionclient_cs", "target": "options", "relation": "imports", "context": "import", "confidence": "EXTRACTED", "source_file": "C:\\Users\\johns\\source\\repos\\MediaBox2026\\MediaBox2026\\Services\\TransmissionClient.cs", "source_location": "L6", "weight": 1.0}, {"source": "c_users_johns_source_repos_mediabox2026_mediabox2026_services_transmissionclient_cs", "target": "services_transmissionclient_transmissionclient", "relation": "contains", "confidence": "EXTRACTED", "source_file": "C:\\Users\\johns\\source\\repos\\MediaBox2026\\MediaBox2026\\Services\\TransmissionClient.cs", "source_location": "L10", "weight": 1.0}, {"source": "services_transmissionclient_transmissionclient", "target": "string", "relation": "references", "confidence": "EXTRACTED", "source_file": "C:\\Users\\johns\\source\\repos\\MediaBox2026\\MediaBox2026\\Services\\TransmissionClient.cs", "source_location": "L12", "weight": 1.0, "context": "field"}, {"source": "services_transmissionclient_transmissionclient", "target": "services_transmissionclient_transmissionclient_addtorrentasync", "relation": "method", "confidence": "EXTRACTED", "source_file": "C:\\Users\\johns\\source\\repos\\MediaBox2026\\MediaBox2026\\Services\\TransmissionClient.cs", "source_location": "L14", "weight": 1.0}, {"source": "services_transmissionclient_transmissionclient_addtorrentasync", "target": "cancellationtoken", "relation": "references", "confidence": "EXTRACTED", "source_file": "C:\\Users\\johns\\source\\repos\\MediaBox2026\\MediaBox2026\\Services\\TransmissionClient.cs", "source_location": "L14", "weight": 1.0, "context": "parameter_type"}, {"source": "services_transmissionclient_transmissionclient_addtorrentasync", "target": "task", "relation": "references", "confidence": "EXTRACTED", "source_file": "C:\\Users\\johns\\source\\repos\\MediaBox2026\\MediaBox2026\\Services\\TransmissionClient.cs", "source_location": "L14", "weight": 1.0, "context": "return_type"}, {"source": "services_transmissionclient_transmissionclient", "target": "services_transmissionclient_transmissionclient_gettorrentsasync", "relation": "method", "confidence": "EXTRACTED", "source_file": "C:\\Users\\johns\\source\\repos\\MediaBox2026\\MediaBox2026\\Services\\TransmissionClient.cs", "source_location": "L35", "weight": 1.0}, {"source": "services_transmissionclient_transmissionclient_gettorrentsasync", "target": "cancellationtoken", "relation": "references", "confidence": "EXTRACTED", "source_file": "C:\\Users\\johns\\source\\repos\\MediaBox2026\\MediaBox2026\\Services\\TransmissionClient.cs", "source_location": "L35", "weight": 1.0, "context": "parameter_type"}, {"source": "services_transmissionclient_transmissionclient_gettorrentsasync", "target": "task", "relation": "references", "confidence": "EXTRACTED", "source_file": "C:\\Users\\johns\\source\\repos\\MediaBox2026\\MediaBox2026\\Services\\TransmissionClient.cs", "source_location": "L35", "weight": 1.0, "context": "return_type"}, {"source": "services_transmissionclient_transmissionclient_gettorrentsasync", "target": "list", "relation": "references", "confidence": "EXTRACTED", "source_file": "C:\\Users\\johns\\source\\repos\\MediaBox2026\\MediaBox2026\\Services\\TransmissionClient.cs", "source_location": "L35", "weight": 1.0, "context": "generic_arg"}, {"source": "services_transmissionclient_transmissionclient_gettorrentsasync", "target": "torrentinfo", "relation": "references", "confidence": "EXTRACTED", "source_file": "C:\\Users\\johns\\source\\repos\\MediaBox2026\\MediaBox2026\\Services\\TransmissionClient.cs", "source_location": "L35", "weight": 1.0, "context": "generic_arg"}, {"source": "services_transmissionclient_transmissionclient", "target": "services_transmissionclient_transmissionclient_removetorrentasync", "relation": "method", "confidence": "EXTRACTED", "source_file": "C:\\Users\\johns\\source\\repos\\MediaBox2026\\MediaBox2026\\Services\\TransmissionClient.cs", "source_location": "L74", "weight": 1.0}, {"source": "services_transmissionclient_transmissionclient_removetorrentasync", "target": "cancellationtoken", "relation": "references", "confidence": "EXTRACTED", "source_file": "C:\\Users\\johns\\source\\repos\\MediaBox2026\\MediaBox2026\\Services\\TransmissionClient.cs", "source_location": "L74", "weight": 1.0, "context": "parameter_type"}, {"source": "services_transmissionclient_transmissionclient_removetorrentasync", "target": "task", "relation": "references", "confidence": "EXTRACTED", "source_file": "C:\\Users\\johns\\source\\repos\\MediaBox2026\\MediaBox2026\\Services\\TransmissionClient.cs", "source_location": "L74", "weight": 1.0, "context": "return_type"}, {"source": "services_transmissionclient_transmissionclient", "target": "services_transmissionclient_transmissionclient_pausetorrentasync", "relation": "method", "confidence": "EXTRACTED", "source_file": "C:\\Users\\johns\\source\\repos\\MediaBox2026\\MediaBox2026\\Services\\TransmissionClient.cs", "source_location": "L89", "weight": 1.0}, {"source": "services_transmissionclient_transmissionclient_pausetorrentasync", "target": "cancellationtoken", "relation": "references", "confidence": "EXTRACTED", "source_file": "C:\\Users\\johns\\source\\repos\\MediaBox2026\\MediaBox2026\\Services\\TransmissionClient.cs", "source_location": "L89", "weight": 1.0, "context": "parameter_type"}, {"source": "services_transmissionclient_transmissionclient_pausetorrentasync", "target": "task", "relation": "references", "confidence": "EXTRACTED", "source_file": "C:\\Users\\johns\\source\\repos\\MediaBox2026\\MediaBox2026\\Services\\TransmissionClient.cs", "source_location": "L89", "weight": 1.0, "context": "return_type"}, {"source": "services_transmissionclient_transmissionclient", "target": "services_transmissionclient_transmissionclient_resumetorrentasync", "relation": "method", "confidence": "EXTRACTED", "source_file": "C:\\Users\\johns\\source\\repos\\MediaBox2026\\MediaBox2026\\Services\\TransmissionClient.cs", "source_location": "L108", "weight": 1.0}, {"source": "services_transmissionclient_transmissionclient_resumetorrentasync", "target": "cancellationtoken", "relation": "references", "confidence": "EXTRACTED", "source_file": "C:\\Users\\johns\\source\\repos\\MediaBox2026\\MediaBox2026\\Services\\TransmissionClient.cs", "source_location": "L108", "weight": 1.0, "context": "parameter_type"}, {"source": "services_transmissionclient_transmissionclient_resumetorrentasync", "target": "task", "relation": "references", "confidence": "EXTRACTED", "source_file": "C:\\Users\\johns\\source\\repos\\MediaBox2026\\MediaBox2026\\Services\\TransmissionClient.cs", "source_location": "L108", "weight": 1.0, "context": "return_type"}, {"source": "services_transmissionclient_transmissionclient", "target": "services_transmissionclient_transmissionclient_getaltspeedenabledasync", "relation": "method", "confidence": "EXTRACTED", "source_file": "C:\\Users\\johns\\source\\repos\\MediaBox2026\\MediaBox2026\\Services\\TransmissionClient.cs", "source_location": "L127", "weight": 1.0}, {"source": "services_transmissionclient_transmissionclient_getaltspeedenabledasync", "target": "cancellationtoken", "relation": "references", "confidence": "EXTRACTED", "source_file": "C:\\Users\\johns\\source\\repos\\MediaBox2026\\MediaBox2026\\Services\\TransmissionClient.cs", "source_location": "L127", "weight": 1.0, "context": "parameter_type"}, {"source": "services_transmissionclient_transmissionclient_getaltspeedenabledasync", "target": "task", "relation": "references", "confidence": "EXTRACTED", "source_file": "C:\\Users\\johns\\source\\repos\\MediaBox2026\\MediaBox2026\\Services\\TransmissionClient.cs", "source_location": "L127", "weight": 1.0, "context": "return_type"}, {"source": "services_transmissionclient_transmissionclient", "target": "services_transmissionclient_transmissionclient_setaltspeedasync", "relation": "method", "confidence": "EXTRACTED", "source_file": "C:\\Users\\johns\\source\\repos\\MediaBox2026\\MediaBox2026\\Services\\TransmissionClient.cs", "source_location": "L145", "weight": 1.0}, {"source": "services_transmissionclient_transmissionclient_setaltspeedasync", "target": "cancellationtoken", "relation": "references", "confidence": "EXTRACTED", "source_file": "C:\\Users\\johns\\source\\repos\\MediaBox2026\\MediaBox2026\\Services\\TransmissionClient.cs", "source_location": "L145", "weight": 1.0, "context": "parameter_type"}, {"source": "services_transmissionclient_transmissionclient_setaltspeedasync", "target": "task", "relation": "references", "confidence": "EXTRACTED", "source_file": "C:\\Users\\johns\\source\\repos\\MediaBox2026\\MediaBox2026\\Services\\TransmissionClient.cs", "source_location": "L145", "weight": 1.0, "context": "return_type"}, {"source": "services_transmissionclient_transmissionclient", "target": "services_transmissionclient_transmissionclient_sendrpcasync", "relation": "method", "confidence": "EXTRACTED", "source_file": "C:\\Users\\johns\\source\\repos\\MediaBox2026\\MediaBox2026\\Services\\TransmissionClient.cs", "source_location": "L164", "weight": 1.0}, {"source": "services_transmissionclient_transmissionclient_sendrpcasync", "target": "jsonobject", "relation": "references", "confidence": "EXTRACTED", "source_file": "C:\\Users\\johns\\source\\repos\\MediaBox2026\\MediaBox2026\\Services\\TransmissionClient.cs", "source_location": "L164", "weight": 1.0, "context": "parameter_type"}, {"source": "services_transmissionclient_transmissionclient_sendrpcasync", "target": "cancellationtoken", "relation": "references", "confidence": "EXTRACTED", "source_file": "C:\\Users\\johns\\source\\repos\\MediaBox2026\\MediaBox2026\\Services\\TransmissionClient.cs", "source_location": "L164", "weight": 1.0, "context": "parameter_type"}, {"source": "services_transmissionclient_transmissionclient_sendrpcasync", "target": "task", "relation": "references", "confidence": "EXTRACTED", "source_file": "C:\\Users\\johns\\source\\repos\\MediaBox2026\\MediaBox2026\\Services\\TransmissionClient.cs", "source_location": "L164", "weight": 1.0, "context": "return_type"}, {"source": "services_transmissionclient_transmissionclient_sendrpcasync", "target": "jsonelement", "relation": "references", "confidence": "EXTRACTED", "source_file": "C:\\Users\\johns\\source\\repos\\MediaBox2026\\MediaBox2026\\Services\\TransmissionClient.cs", "source_location": "L164", "weight": 1.0, "context": "generic_arg"}, {"source": "services_transmissionclient_transmissionclient_addtorrentasync", "target": "services_transmissionclient_transmissionclient_sendrpcasync", "relation": "calls", "context": "call", "confidence": "EXTRACTED", "source_file": "C:\\Users\\johns\\source\\repos\\MediaBox2026\\MediaBox2026\\Services\\TransmissionClient.cs", "source_location": "L26", "weight": 1.0}, {"source": "services_transmissionclient_transmissionclient_gettorrentsasync", "target": "services_transmissionclient_transmissionclient_sendrpcasync", "relation": "calls", "context": "call", "confidence": "EXTRACTED", "source_file": "C:\\Users\\johns\\source\\repos\\MediaBox2026\\MediaBox2026\\Services\\TransmissionClient.cs", "source_location": "L50", "weight": 1.0}, {"source": "services_transmissionclient_transmissionclient_removetorrentasync", "target": "services_transmissionclient_transmissionclient_sendrpcasync", "relation": "calls", "context": "call", "confidence": "EXTRACTED", "source_file": "C:\\Users\\johns\\source\\repos\\MediaBox2026\\MediaBox2026\\Services\\TransmissionClient.cs", "source_location": "L85", "weight": 1.0}, {"source": "services_transmissionclient_transmissionclient_pausetorrentasync", "target": "services_transmissionclient_transmissionclient_sendrpcasync", "relation": "calls", "context": "call", "confidence": "EXTRACTED", "source_file": "C:\\Users\\johns\\source\\repos\\MediaBox2026\\MediaBox2026\\Services\\TransmissionClient.cs", "source_location": "L99", "weight": 1.0}, {"source": "services_transmissionclient_transmissionclient_resumetorrentasync", "target": "services_transmissionclient_transmissionclient_sendrpcasync", "relation": "calls", "context": "call", "confidence": "EXTRACTED", "source_file": "C:\\Users\\johns\\source\\repos\\MediaBox2026\\MediaBox2026\\Services\\TransmissionClient.cs", "source_location": "L118", "weight": 1.0}, {"source": "services_transmissionclient_transmissionclient_getaltspeedenabledasync", "target": "services_transmissionclient_transmissionclient_sendrpcasync", "relation": "calls", "context": "call", "confidence": "EXTRACTED", "source_file": "C:\\Users\\johns\\source\\repos\\MediaBox2026\\MediaBox2026\\Services\\TransmissionClient.cs", "source_location": "L137", "weight": 1.0}, {"source": "services_transmissionclient_transmissionclient_setaltspeedasync", "target": "services_transmissionclient_transmissionclient_sendrpcasync", "relation": "calls", "context": "call", "confidence": "EXTRACTED", "source_file": "C:\\Users\\johns\\source\\repos\\MediaBox2026\\MediaBox2026\\Services\\TransmissionClient.cs", "source_location": "L155", "weight": 1.0}], "raw_calls": [{"caller_nid": "services_transmissionclient_transmissionclient_addtorrentasync", "callee": "LogInformation", "is_member_call": true, "source_file": "C:\\Users\\johns\\source\\repos\\MediaBox2026\\MediaBox2026\\Services\\TransmissionClient.cs", "source_location": "L29"}, {"caller_nid": "services_transmissionclient_transmissionclient_gettorrentsasync", "callee": "Add", "is_member_call": true, "source_file": "C:\\Users\\johns\\source\\repos\\MediaBox2026\\MediaBox2026\\Services\\TransmissionClient.cs", "source_location": "L39"}, {"caller_nid": "services_transmissionclient_transmissionclient_gettorrentsasync", "callee": "Create", "is_member_call": true, "source_file": "C:\\Users\\johns\\source\\repos\\MediaBox2026\\MediaBox2026\\Services\\TransmissionClient.cs", "source_location": "L39"}, {"caller_nid": "services_transmissionclient_transmissionclient_gettorrentsasync", "callee": "TryGetProperty", "is_member_call": true, "source_file": "C:\\Users\\johns\\source\\repos\\MediaBox2026\\MediaBox2026\\Services\\TransmissionClient.cs", "source_location": "L54"}, {"caller_nid": "services_transmissionclient_transmissionclient_gettorrentsasync", "callee": "TryGetProperty", "is_member_call": true, "source_file": "C:\\Users\\johns\\source\\repos\\MediaBox2026\\MediaBox2026\\Services\\TransmissionClient.cs", "source_location": "L55"}, {"caller_nid": "services_transmissionclient_transmissionclient_gettorrentsasync", "callee": "EnumerateArray", "is_member_call": true, "source_file": "C:\\Users\\johns\\source\\repos\\MediaBox2026\\MediaBox2026\\Services\\TransmissionClient.cs", "source_location": "L57"}, {"caller_nid": "services_transmissionclient_transmissionclient_gettorrentsasync", "callee": "Add", "is_member_call": true, "source_file": "C:\\Users\\johns\\source\\repos\\MediaBox2026\\MediaBox2026\\Services\\TransmissionClient.cs", "source_location": "L59"}, {"caller_nid": "services_transmissionclient_transmissionclient_gettorrentsasync", "callee": "GetInt32", "is_member_call": true, "source_file": "C:\\Users\\johns\\source\\repos\\MediaBox2026\\MediaBox2026\\Services\\TransmissionClient.cs", "source_location": "L61"}, {"caller_nid": "services_transmissionclient_transmissionclient_gettorrentsasync", "callee": "GetProperty", "is_member_call": true, "source_file": "C:\\Users\\johns\\source\\repos\\MediaBox2026\\MediaBox2026\\Services\\TransmissionClient.cs", "source_location": "L61"}, {"caller_nid": "services_transmissionclient_transmissionclient_gettorrentsasync", "callee": "GetString", "is_member_call": true, "source_file": "C:\\Users\\johns\\source\\repos\\MediaBox2026\\MediaBox2026\\Services\\TransmissionClient.cs", "source_location": "L62"}, {"caller_nid": "services_transmissionclient_transmissionclient_gettorrentsasync", "callee": "GetProperty", "is_member_call": true, "source_file": "C:\\Users\\johns\\source\\repos\\MediaBox2026\\MediaBox2026\\Services\\TransmissionClient.cs", "source_location": "L62"}, {"caller_nid": "services_transmissionclient_transmissionclient_gettorrentsasync", "callee": "GetInt32", "is_member_call": true, "source_file": "C:\\Users\\johns\\source\\repos\\MediaBox2026\\MediaBox2026\\Services\\TransmissionClient.cs", "source_location": "L63"}, {"caller_nid": "services_transmissionclient_transmissionclient_gettorrentsasync", "callee": "GetProperty", "is_member_call": true, "source_file": "C:\\Users\\johns\\source\\repos\\MediaBox2026\\MediaBox2026\\Services\\TransmissionClient.cs", "source_location": "L63"}, {"caller_nid": "services_transmissionclient_transmissionclient_gettorrentsasync", "callee": "GetDouble", "is_member_call": true, "source_file": "C:\\Users\\johns\\source\\repos\\MediaBox2026\\MediaBox2026\\Services\\TransmissionClient.cs", "source_location": "L64"}, {"caller_nid": "services_transmissionclient_transmissionclient_gettorrentsasync", "callee": "GetProperty", "is_member_call": true, "source_file": "C:\\Users\\johns\\source\\repos\\MediaBox2026\\MediaBox2026\\Services\\TransmissionClient.cs", "source_location": "L64"}, {"caller_nid": "services_transmissionclient_transmissionclient_gettorrentsasync", "callee": "GetInt64", "is_member_call": true, "source_file": "C:\\Users\\johns\\source\\repos\\MediaBox2026\\MediaBox2026\\Services\\TransmissionClient.cs", "source_location": "L65"}, {"caller_nid": "services_transmissionclient_transmissionclient_gettorrentsasync", "callee": "GetProperty", "is_member_call": true, "source_file": "C:\\Users\\johns\\source\\repos\\MediaBox2026\\MediaBox2026\\Services\\TransmissionClient.cs", "source_location": "L65"}, {"caller_nid": "services_transmissionclient_transmissionclient_gettorrentsasync", "callee": "TryGetProperty", "is_member_call": true, "source_file": "C:\\Users\\johns\\source\\repos\\MediaBox2026\\MediaBox2026\\Services\\TransmissionClient.cs", "source_location": "L66"}, {"caller_nid": "services_transmissionclient_transmissionclient_gettorrentsasync", "callee": "GetString", "is_member_call": true, "source_file": "C:\\Users\\johns\\source\\repos\\MediaBox2026\\MediaBox2026\\Services\\TransmissionClient.cs", "source_location": "L66"}, {"caller_nid": "services_transmissionclient_transmissionclient_gettorrentsasync", "callee": "TryGetProperty", "is_member_call": true, "source_file": "C:\\Users\\johns\\source\\repos\\MediaBox2026\\MediaBox2026\\Services\\TransmissionClient.cs", "source_location": "L67"}, {"caller_nid": "services_transmissionclient_transmissionclient_gettorrentsasync", "callee": "GetInt64", "is_member_call": true, "source_file": "C:\\Users\\johns\\source\\repos\\MediaBox2026\\MediaBox2026\\Services\\TransmissionClient.cs", "source_location": "L67"}, {"caller_nid": "services_transmissionclient_transmissionclient_removetorrentasync", "callee": "Create", "is_member_call": true, "source_file": "C:\\Users\\johns\\source\\repos\\MediaBox2026\\MediaBox2026\\Services\\TransmissionClient.cs", "source_location": "L81"}, {"caller_nid": "services_transmissionclient_transmissionclient_removetorrentasync", "callee": "LogInformation", "is_member_call": true, "source_file": "C:\\Users\\johns\\source\\repos\\MediaBox2026\\MediaBox2026\\Services\\TransmissionClient.cs", "source_location": "L86"}, {"caller_nid": "services_transmissionclient_transmissionclient_pausetorrentasync", "callee": "Create", "is_member_call": true, "source_file": "C:\\Users\\johns\\source\\repos\\MediaBox2026\\MediaBox2026\\Services\\TransmissionClient.cs", "source_location": "L96"}, {"caller_nid": "services_transmissionclient_transmissionclient_pausetorrentasync", "callee": "LogInformation", "is_member_call": true, "source_file": "C:\\Users\\johns\\source\\repos\\MediaBox2026\\MediaBox2026\\Services\\TransmissionClient.cs", "source_location": "L102"}, {"caller_nid": "services_transmissionclient_transmissionclient_resumetorrentasync", "callee": "Create", "is_member_call": true, "source_file": "C:\\Users\\johns\\source\\repos\\MediaBox2026\\MediaBox2026\\Services\\TransmissionClient.cs", "source_location": "L115"}, {"caller_nid": "services_transmissionclient_transmissionclient_resumetorrentasync", "callee": "LogInformation", "is_member_call": true, "source_file": "C:\\Users\\johns\\source\\repos\\MediaBox2026\\MediaBox2026\\Services\\TransmissionClient.cs", "source_location": "L121"}, {"caller_nid": "services_transmissionclient_transmissionclient_getaltspeedenabledasync", "callee": "Create", "is_member_call": true, "source_file": "C:\\Users\\johns\\source\\repos\\MediaBox2026\\MediaBox2026\\Services\\TransmissionClient.cs", "source_location": "L134"}, {"caller_nid": "services_transmissionclient_transmissionclient_getaltspeedenabledasync", "callee": "TryGetProperty", "is_member_call": true, "source_file": "C:\\Users\\johns\\source\\repos\\MediaBox2026\\MediaBox2026\\Services\\TransmissionClient.cs", "source_location": "L139"}, {"caller_nid": "services_transmissionclient_transmissionclient_getaltspeedenabledasync", "callee": "TryGetProperty", "is_member_call": true, "source_file": "C:\\Users\\johns\\source\\repos\\MediaBox2026\\MediaBox2026\\Services\\TransmissionClient.cs", "source_location": "L140"}, {"caller_nid": "services_transmissionclient_transmissionclient_getaltspeedenabledasync", "callee": "GetBoolean", "is_member_call": true, "source_file": "C:\\Users\\johns\\source\\repos\\MediaBox2026\\MediaBox2026\\Services\\TransmissionClient.cs", "source_location": "L141"}, {"caller_nid": "services_transmissionclient_transmissionclient_setaltspeedasync", "callee": "LogInformation", "is_member_call": true, "source_file": "C:\\Users\\johns\\source\\repos\\MediaBox2026\\MediaBox2026\\Services\\TransmissionClient.cs", "source_location": "L158"}, {"caller_nid": "services_transmissionclient_transmissionclient_sendrpcasync", "callee": "CreateClient", "is_member_call": true, "source_file": "C:\\Users\\johns\\source\\repos\\MediaBox2026\\MediaBox2026\\Services\\TransmissionClient.cs", "source_location": "L167"}, {"caller_nid": "services_transmissionclient_transmissionclient_sendrpcasync", "callee": "IsNullOrEmpty", "is_member_call": true, "source_file": "C:\\Users\\johns\\source\\repos\\MediaBox2026\\MediaBox2026\\Services\\TransmissionClient.cs", "source_location": "L169"}, {"caller_nid": "services_transmissionclient_transmissionclient_sendrpcasync", "callee": "GetBytes", "is_member_call": true, "source_file": "C:\\Users\\johns\\source\\repos\\MediaBox2026\\MediaBox2026\\Services\\TransmissionClient.cs", "source_location": "L171"}, {"caller_nid": "services_transmissionclient_transmissionclient_sendrpcasync", "callee": "ToBase64String", "is_member_call": true, "source_file": "C:\\Users\\johns\\source\\repos\\MediaBox2026\\MediaBox2026\\Services\\TransmissionClient.cs", "source_location": "L172"}, {"caller_nid": "services_transmissionclient_transmissionclient_sendrpcasync", "callee": "Add", "is_member_call": true, "source_file": "C:\\Users\\johns\\source\\repos\\MediaBox2026\\MediaBox2026\\Services\\TransmissionClient.cs", "source_location": "L176"}, {"caller_nid": "services_transmissionclient_transmissionclient_sendrpcasync", "callee": "ToJsonString", "is_member_call": true, "source_file": "C:\\Users\\johns\\source\\repos\\MediaBox2026\\MediaBox2026\\Services\\TransmissionClient.cs", "source_location": "L178"}, {"caller_nid": "services_transmissionclient_transmissionclient_sendrpcasync", "callee": "LogInformation", "is_member_call": true, "source_file": "C:\\Users\\johns\\source\\repos\\MediaBox2026\\MediaBox2026\\Services\\TransmissionClient.cs", "source_location": "L179"}, {"caller_nid": "services_transmissionclient_transmissionclient_sendrpcasync", "callee": "PostAsync", "is_member_call": true, "source_file": "C:\\Users\\johns\\source\\repos\\MediaBox2026\\MediaBox2026\\Services\\TransmissionClient.cs", "source_location": "L182"}, {"caller_nid": "services_transmissionclient_transmissionclient_sendrpcasync", "callee": "TryGetValues", "is_member_call": true, "source_file": "C:\\Users\\johns\\source\\repos\\MediaBox2026\\MediaBox2026\\Services\\TransmissionClient.cs", "source_location": "L186"}, {"caller_nid": "services_transmissionclient_transmissionclient_sendrpcasync", "callee": "FirstOrDefault", "is_member_call": true, "source_file": "C:\\Users\\johns\\source\\repos\\MediaBox2026\\MediaBox2026\\Services\\TransmissionClient.cs", "source_location": "L188"}, {"caller_nid": "services_transmissionclient_transmissionclient_sendrpcasync", "callee": "LogWarning", "is_member_call": true, "source_file": "C:\\Users\\johns\\source\\repos\\MediaBox2026\\MediaBox2026\\Services\\TransmissionClient.cs", "source_location": "L192"}, {"caller_nid": "services_transmissionclient_transmissionclient_sendrpcasync", "callee": "LogWarning", "is_member_call": true, "source_file": "C:\\Users\\johns\\source\\repos\\MediaBox2026\\MediaBox2026\\Services\\TransmissionClient.cs", "source_location": "L198"}, {"caller_nid": "services_transmissionclient_transmissionclient_sendrpcasync", "callee": "ReadAsStringAsync", "is_member_call": true, "source_file": "C:\\Users\\johns\\source\\repos\\MediaBox2026\\MediaBox2026\\Services\\TransmissionClient.cs", "source_location": "L202"}, {"caller_nid": "services_transmissionclient_transmissionclient_sendrpcasync", "callee": "Parse", "is_member_call": true, "source_file": "C:\\Users\\johns\\source\\repos\\MediaBox2026\\MediaBox2026\\Services\\TransmissionClient.cs", "source_location": "L203"}, {"caller_nid": "services_transmissionclient_transmissionclient_sendrpcasync", "callee": "TryGetProperty", "is_member_call": true, "source_file": "C:\\Users\\johns\\source\\repos\\MediaBox2026\\MediaBox2026\\Services\\TransmissionClient.cs", "source_location": "L206"}, {"caller_nid": "services_transmissionclient_transmissionclient_sendrpcasync", "callee": "GetString", "is_member_call": true, "source_file": "C:\\Users\\johns\\source\\repos\\MediaBox2026\\MediaBox2026\\Services\\TransmissionClient.cs", "source_location": "L206"}, {"caller_nid": "services_transmissionclient_transmissionclient_sendrpcasync", "callee": "LogWarning", "is_member_call": true, "source_file": "C:\\Users\\johns\\source\\repos\\MediaBox2026\\MediaBox2026\\Services\\TransmissionClient.cs", "source_location": "L209"}, {"caller_nid": "services_transmissionclient_transmissionclient_sendrpcasync", "callee": "GetString", "is_member_call": true, "source_file": "C:\\Users\\johns\\source\\repos\\MediaBox2026\\MediaBox2026\\Services\\TransmissionClient.cs", "source_location": "L209"}, {"caller_nid": "services_transmissionclient_transmissionclient_sendrpcasync", "callee": "GetProperty", "is_member_call": true, "source_file": "C:\\Users\\johns\\source\\repos\\MediaBox2026\\MediaBox2026\\Services\\TransmissionClient.cs", "source_location": "L209"}]}